sphinx_rapidoc/__init__.py
sphinx_rapidoc/static/rapidoc.min.js
sphinx_rapidoc/templates/rapidoc.html
sphinx_rapidoc-0.1.2.dist-info/licenses/LICENSE
tests/__init__.py
tests/conftest.py
tests/test_rapidoc.py
sphinx_rapidoc-0.1.2.dist-info/METADATA
sphinx_rapidoc-0.1.2.dist-info/WHEEL
sphinx_rapidoc-0.1.2.dist-info/entry_points.txt
sphinx_rapidoc-0.1.2.dist-info/top_level.txt
sphinx_rapidoc-0.1.2.dist-info/RECORD
