Metadata-Version: 2.4
Name: sphinx_rapidoc
Version: 0.1.2
Summary: Custom Sphinx extension for embedding RapiDoc in your documentation
Home-page: https://github.com/TirthS24/sphinx_rapidoc
Author: Tirth Shah
Classifier: Programming Language :: Python :: 3
Classifier: License :: OSI Approved :: MIT License
Classifier: Operating System :: OS Independent
Requires-Python: >=3.9
License-File: LICENSE
Requires-Dist: sphinx>=7.2.5
Dynamic: author
Dynamic: classifier
Dynamic: description
Dynamic: description-content-type
Dynamic: home-page
Dynamic: license-file
Dynamic: requires-dist
Dynamic: requires-python
Dynamic: summary
